Metadata-Version: 1.1
Name: django-jsonschema
Version: 0.2.0
Summary: django-jsonschema converts Django Forms into JSON Schema compatibile representations
Home-page: http://github.com/celerityweb/django-jsonschema
Author: Jason Kraus
Author-email: zbyte64@gmail.com
License: New BSD License
Keywords: django json schema
Platform: UNKNOWN
Classifier: Programming Language :: Python
Classifier: Environment :: Web Environment
Classifier: Framework :: Django
Classifier: Operating System :: OS Independent
Classifier: Natural Language :: English
Classifier: Development Status :: 4 - Beta
Classifier: Intended Audience :: Developers
Classifier: License :: OSI Approved :: BSD License
Classifier: Topic :: Internet :: WWW/HTTP :: Dynamic Content
